genericsuite_ai/__init__.py
genericsuite_ai/chalicelib/endpoints/__init__.py
genericsuite_ai/chalicelib/endpoints/ai_chatbot_endpoint.py
genericsuite_ai/chalicelib/endpoints/ai_conversations_conversion.py
genericsuite_ai/chalicelib/util/__init__.py
genericsuite_ai/chalicelib/util/create_app.py
genericsuite_ai/config/__init__.py
genericsuite_ai/config/config.py
genericsuite_ai/fastapilib/endpoints/__init__.py
genericsuite_ai/fastapilib/endpoints/ai_chatbot_endpoint.py
genericsuite_ai/fastapilib/util/__init__.py
genericsuite_ai/fastapilib/util/create_app.py
genericsuite_ai/flasklib/endpoints/__init__.py
genericsuite_ai/flasklib/endpoints/ai_chatbot_endpoint.py
genericsuite_ai/lib/__init__.py
genericsuite_ai/lib/ai_audio_processing.py
genericsuite_ai/lib/ai_chatbot_commons.py
genericsuite_ai/lib/ai_chatbot_endpoint.py
genericsuite_ai/lib/ai_chatbot_main_langchain.py
genericsuite_ai/lib/ai_chatbot_main_langchain_ca.py
genericsuite_ai/lib/ai_chatbot_main_openai.py
genericsuite_ai/lib/ai_conversations.py
genericsuite_ai/lib/ai_conversations_conversion.py
genericsuite_ai/lib/ai_embeddings.py
genericsuite_ai/lib/ai_gpt_fn_conversations.py
genericsuite_ai/lib/ai_gpt_functions.py
genericsuite_ai/lib/ai_image_generator.py
genericsuite_ai/lib/ai_langchain_models.py
genericsuite_ai/lib/ai_langchain_models_abstract.py
genericsuite_ai/lib/ai_langchain_tools.py
genericsuite_ai/lib/ai_sub_bots.py
genericsuite_ai/lib/ai_utilities.py
genericsuite_ai/lib/ai_vision.py
genericsuite_ai/lib/amazon_bedrock.py
genericsuite_ai/lib/clarifai.py
genericsuite_ai/lib/gcp.py
genericsuite_ai/lib/git_reader.py
genericsuite_ai/lib/huggingface.py
genericsuite_ai/lib/ibm.py
genericsuite_ai/lib/json_reader.py
genericsuite_ai/lib/pdf_reader.py
genericsuite_ai/lib/translator.py
genericsuite_ai/lib/vector_index.py
genericsuite_ai/lib/web_scraping.py
genericsuite_ai/lib/web_search.py
genericsuite_ai/lib/youtube_reader.py
genericsuite_ai/models/__init__.py
genericsuite_ai/models/billing/__init__.py
genericsuite_ai-0.2.0.dist-info/METADATA
genericsuite_ai-0.2.0.dist-info/WHEEL
genericsuite_ai-0.2.0.dist-info/licenses/LICENSE
genericsuite_ai-0.2.0.dist-info/RECORD
